qbittorrent_ark/__init__.py
qbittorrent_ark/__main__.py
qbittorrent_ark/args_parsing.py
qbittorrent_ark/ark.py
qbittorrent_ark/common.py
qbittorrent_ark/main.py
qbittorrent_ark/qbittorrent_logic.py
qbittorrent_ark-0.1.4.dist-info/licenses/LICENSE
qbittorrent_ark-0.1.4.dist-info/METADATA
qbittorrent_ark-0.1.4.dist-info/WHEEL
qbittorrent_ark-0.1.4.dist-info/entry_points.txt
qbittorrent_ark-0.1.4.dist-info/top_level.txt
qbittorrent_ark-0.1.4.dist-info/RECORD
