Metadata-Version: 2.4
Name: qbittorrent_ark
Version: 0.1.4
Summary: gui for smalk krypto testing .
Author-email: The220th <The220th@gmail.com>
License-Expression: MIT
Project-URL: Homepage, https://github.com/The220th/qbittorrent_ark
Project-URL: Issues, https://github.com/The220th/qbittorrent_ark/issues
Classifier: Programming Language :: Python :: 3
Classifier: Operating System :: POSIX :: Linux
Requires-Python: >=3.7
License-File: LICENSE
Requires-Dist: ksupk
Requires-Dist: python-qbittorrent==0.4.3
Requires-Dist: pyyaml
Requires-Dist: argparse
Requires-Dist: requests
Dynamic: license-file
